pyahotts/__init__.py
pyahotts/libhtts_aarch64.so
pyahotts/libhtts_x86_64.so
pyahotts/version.py
pyahotts/data_tts/dicts/es_dicc.dic
pyahotts/data_tts/dicts/eu_dicc.dic
pyahotts/data_tts/voices/aholab_es_female/bap.pdf
pyahotts/data_tts/voices/aholab_es_female/bap.win1
pyahotts/data_tts/voices/aholab_es_female/bap.win2
pyahotts/data_tts/voices/aholab_es_female/bap.win3
pyahotts/data_tts/voices/aholab_es_female/dur.pdf
pyahotts/data_tts/voices/aholab_es_female/gv-bap.pdf
pyahotts/data_tts/voices/aholab_es_female/gv-lf0.pdf
pyahotts/data_tts/voices/aholab_es_female/gv-mgc.pdf
pyahotts/data_tts/voices/aholab_es_female/gv-switch.inf
pyahotts/data_tts/voices/aholab_es_female/lf0.pdf
pyahotts/data_tts/voices/aholab_es_female/lf0.win1
pyahotts/data_tts/voices/aholab_es_female/lf0.win2
pyahotts/data_tts/voices/aholab_es_female/lf0.win3
pyahotts/data_tts/voices/aholab_es_female/mgc.pdf
pyahotts/data_tts/voices/aholab_es_female/mgc.win1
pyahotts/data_tts/voices/aholab_es_female/mgc.win2
pyahotts/data_tts/voices/aholab_es_female/mgc.win3
pyahotts/data_tts/voices/aholab_es_female/receta.txt
pyahotts/data_tts/voices/aholab_es_female/tree-bap.inf
pyahotts/data_tts/voices/aholab_es_female/tree-dur.inf
pyahotts/data_tts/voices/aholab_es_female/tree-gv-bap.inf
pyahotts/data_tts/voices/aholab_es_female/tree-gv-lf0.inf
pyahotts/data_tts/voices/aholab_es_female/tree-gv-mgc.inf
pyahotts/data_tts/voices/aholab_es_female/tree-lf0.inf
pyahotts/data_tts/voices/aholab_es_female/tree-mgc.inf
pyahotts/data_tts/voices/aholab_es_female/voiceid
pyahotts/data_tts/voices/aholab_eu_female/bap.pdf
pyahotts/data_tts/voices/aholab_eu_female/bap.win1
pyahotts/data_tts/voices/aholab_eu_female/bap.win2
pyahotts/data_tts/voices/aholab_eu_female/bap.win3
pyahotts/data_tts/voices/aholab_eu_female/dur.pdf
pyahotts/data_tts/voices/aholab_eu_female/gv-bap.pdf
pyahotts/data_tts/voices/aholab_eu_female/gv-lf0.pdf
pyahotts/data_tts/voices/aholab_eu_female/gv-mgc.pdf
pyahotts-0.0.1.dist-info/LICENSE
pyahotts-0.0.1.dist-info/METADATA
pyahotts-0.0.1.dist-info/WHEEL
pyahotts-0.0.1.dist-info/top_level.txt
pyahotts-0.0.1.dist-info/RECORD
