Metadata-Version: 2.1
Name: pyahotts
Version: 0.0.1
Summary: AhoTTS - python Text-to-Speech package
Home-page: https://github.com/TigreGotico/pyAhoTTS
Author: JarbasAI
Author-email: jarbasai@mailfence.com
Classifier: Programming Language :: Python :: 3
Classifier: License :: OSI Approved :: MIT License
Classifier: Operating System :: OS Independent
Requires-Python: >=3.6
License-File: LICENSE
Requires-Dist: numpy
